PyMyMethods/Method.py
PyMyMethods/__init__.py
PyMyMethods/parentMethod.py
PyMyMethods-1.0.6.dist-info/METADATA
PyMyMethods-1.0.6.dist-info/WHEEL
PyMyMethods-1.0.6.dist-info/top_level.txt
PyMyMethods-1.0.6.dist-info/RECORD
